lymcp/__init__.py
lymcp/api.py
lymcp/py.typed
lymcp/server.py
lymcp/translate.py
lymcp-0.2.2.dist-info/METADATA
lymcp-0.2.2.dist-info/WHEEL
lymcp-0.2.2.dist-info/entry_points.txt
lymcp-0.2.2.dist-info/licenses/LICENSE
lymcp-0.2.2.dist-info/RECORD
